README.rst
setup.cfg
setup.py
business_duration/__init__.py
business_duration.egg-info/PKG-INFO
business_duration.egg-info/SOURCES.txt
business_duration.egg-info/dependency_links.txt
business_duration.egg-info/not-zip-safe
business_duration.egg-info/requires.txt
business_duration.egg-info/top_level.txt